agentmap/__init__.py
agentmap/_version.py
agentmap/builtin_definition_constants.py
agentmap/cli.py
agentmap/runtime_api.py
agentmap/server_cli.py
agentmap/agents/__init__.py
agentmap/agents/base_agent.py
agentmap/agents/builtins/__init__.py
agentmap/agents/builtins/branching_agent.py
agentmap/agents/builtins/default_agent.py
agentmap/agents/builtins/echo_agent.py
agentmap/agents/builtins/failure_agent.py
agentmap/agents/builtins/graph_agent.py
agentmap/agents/builtins/human_agent.py
agentmap/agents/builtins/input_agent.py
agentmap/agents/builtins/orchestrator_agent.py
agentmap/agents/builtins/success_agent.py
agentmap/agents/builtins/summary_agent.py
agentmap/agents/builtins/suspend_agent.py
agentmap/agents/builtins/tool_agent.py
agentmap/agents/builtins/llm/__init__.py
agentmap/agents/builtins/llm/anthropic_agent.py
agentmap/agents/builtins/llm/google_agent.py
agentmap/agents/builtins/llm/llm_agent.py
agentmap/agents/builtins/llm/memory.py
agentmap/agents/builtins/llm/openai_agent.py
agentmap/agents/builtins/storage/__init__.py
agentmap/agents/builtins/storage/base_storage_agent.py
agentmap/agents/builtins/storage/blob/__init__.py
agentmap/agents/builtins/storage/blob/blob_reader_agent.py
agentmap/agents/builtins/storage/blob/blob_writer_agent.py
agentmap/agents/builtins/storage/blob/readme.md
agentmap/agents/builtins/storage/csv/__init__.py
agentmap/agents/builtins/storage/csv/base_agent.py
agentmap/agents/builtins/storage/csv/reader.py
agentmap/agents/builtins/storage/csv/writer.py
agentmap/agents/builtins/storage/document/__init__.py
agentmap/agents/builtins/storage/document/base_agent.py
agentmap/agents/builtins/storage/document/path_mixin.py
agentmap/agents/builtins/storage/document/reader.py
agentmap/agents/builtins/storage/document/writer.py
agentmap/agents/builtins/storage/file/__init__.py
agentmap/agents/builtins/storage/file/reader.py
agentmap/agents/builtins/storage/file/writer.py
agentmap/agents/builtins/storage/json/__init__.py
agentmap-0.9.104.dist-info/METADATA
agentmap-0.9.104.dist-info/WHEEL
agentmap-0.9.104.dist-info/entry_points.txt
agentmap-0.9.104.dist-info/licenses/LICENSE
agentmap-0.9.104.dist-info/RECORD
