Metadata-Version: 2.4
Name: agentmap
Version: 0.9.104
Summary: AgentMap: Build and deploy LangGraph agentic workflows from CSV files for fun and profit!
Project-URL: Homepage, https://jwwelbor.github.io/AgentMap
Project-URL: Repository, https://github.com/jwwelbor/AgentMap
Project-URL: Documentation, https://jwwelbor.github.io/AgentMap
Project-URL: Bug Tracker, https://github.com/jwwelbor/AgentMap/issues
Project-URL: Changelog, https://github.com/jwwelbor/AgentMap/blob/main/CHANGELOG.md
Author-email: John Welborn <jwwelbor@gmail.com>
License-Expression: MIT
License-File: LICENSE
Keywords: agents,ai,automation,csv,langgraph,workflows
Classifier: Development Status :: 4 - Beta
Classifier: Intended Audience :: Developers
Classifier: License :: OSI Approved :: MIT License
Classifier: Operating System :: OS Independent
Classifier: Programming Language :: Python :: 3
Classifier: Programming Language :: Python :: 3.11
Classifier: Programming Language :: Python :: 3.12
Classifier: Topic :: Scientific/Engineering :: Artificial Intelligence
Classifier: Topic :: Software Development :: Libraries :: Python Modules
Requires-Python: <4.0,>=3.11
Requires-Dist: autoflake<3,>=2.3.1
Requires-Dist: dependency-injector>=4.41.0
Requires-Dist: dill>=0.3.6
Requires-Dist: fastapi>=0.111.0
Requires-Dist: httpx>=0.27.0
Requires-Dist: langchain-community>=0.3.23
Requires-Dist: langchain-core>=0.1.0
Requires-Dist: langchain>=0.1.0
Requires-Dist: langgraph<0.4.0,>=0.3.5
Requires-Dist: packaging>=23.0
Requires-Dist: pandas>=2.2.1
Requires-Dist: pathvalidate<4,>=3.3.1
Requires-Dist: pydantic>=2.6.3
Requires-Dist: python-multipart>=0.0.9
Requires-Dist: pyyaml>=6.0.0
Requires-Dist: toml<0.11,>=0.10.2
Requires-Dist: typer>=0.12.3
Requires-Dist: uvicorn<0.35,>=0.34.3
Provides-Extra: all
Requires-Dist: chromadb; extra == 'all'
Requires-Dist: firebase-admin; extra == 'all'
Requires-Dist: langchain-anthropic<0.4.0,>=0.3.13; extra == 'all'
Requires-Dist: langchain-google-genai; extra == 'all'
Requires-Dist: langchain-openai>=0.3.17; extra == 'all'
Requires-Dist: langsmith; extra == 'all'
Requires-Dist: python-docx; extra == 'all'
Requires-Dist: unstructured; extra == 'all'
Provides-Extra: llm
Requires-Dist: langchain-anthropic<0.4.0,>=0.3.13; extra == 'llm'
Requires-Dist: langchain-google-genai; extra == 'llm'
Requires-Dist: langchain-openai>=0.3.17; extra == 'llm'
Requires-Dist: langsmith; extra == 'llm'
Provides-Extra: storage
Requires-Dist: chromadb; extra == 'storage'
Requires-Dist: firebase-admin; extra == 'storage'
Requires-Dist: python-docx; extra == 'storage'
Requires-Dist: unstructured; extra == 'storage'
